plotdf/__init__.py
plotdf-0.1.dist-info/pbr.json
plotdf-0.1.dist-info/metadata.json
plotdf-0.1.dist-info/RECORD
plotdf-0.1.dist-info/DESCRIPTION.rst
plotdf-0.1.dist-info/METADATA
plotdf-0.1.dist-info/WHEEL
plotdf-0.1.dist-info/top_level.txt
