Metadata-Version: 2.0
Name: plotdf
Version: 0.1
Summary: Plot phase portraits of 2D differential equations
Home-page: https://github.com/jmoy/plotdf
Author: Jyotirmoy Bhattacharya
Author-email: jyotirmoy@jyotirmoy.net
License: GPLv3
Keywords: matplotlib differential-equations numerics plot
Platform: UNKNOWN
Classifier: Development Status :: 3 - Alpha
Classifier: License :: OSI Approved :: GNU General Public License v3 (GPLv3)
Classifier: Programming Language :: Python :: 2
Classifier: Programming Language :: Python :: 3
Requires-Dist: numpy
Requires-Dist: matplotlib
Requires-Dist: scipy
